{
  "teams": [
    {
      "TeamName": "Nike",
      "TeamLogo": "Nike.png",
      "Location": "Noida",
      "TeamId": "TR001",
      "status": "Amber",
      "id": 1
    },
    {
      "TeamName": "Titans",
      "TeamLogo": "Titans.png",
      "Location": "Noida",
      "TeamId": "TR002",
      "status": "Amber",
      "id": 2
    },
    {
      "TeamName": "Hades",
      "TeamLogo": "Hades.png",
      "Location": "Noida",
      "TeamId": "TR003",
      "status": "Amber",
      "id": 3
    },
    {
      "TeamName": "Caerus",
      "TeamLogo": "Caerus",
      "Location": "Sydney",
      "TeamId": "T869",
      "status": "Amber",
      "id": 4
    },
    {
      "TeamName": "Athena",
      "TeamLogo": "Athena",
      "Location": "Sydney",
      "TeamId": "T41",
      "status": "green",
      "id": 5
    }
  ],
  "features": [
    {
      "id": 1,
      "status": "InProgress"
    },
    {
      "id": 2,
      "status": "Backlog"
    },
    {
      "id": 3,
      "status": "Backlog"
    },
    {
      "id": 4,
      "status": "InProgress"
    },
    {
      "id": 5,
      "Tasks": "WorkRequest",
      "AssignedTo": "ammo",
      "FeatureId": "FR005",
      "WorkRequestInfo": "NA",
      "TeamId": "TR002",
      "status": "Backlog"
    },
    {
      "id": 6,
      "Tasks": "CI",
      "AssignedTo": "Apkl",
      "FeatureId": "FR006",
      "WorkRequestInfo": "checker",
      "TeamId": "TR003",
      "status": "Backlog"
    },
    {
      "id": 7,
      "Tasks": "CI",
      "AssignedTo": "Amit",
      "FeatureId": "FR007",
      "WorkRequestInfo": "chekkk",
      "TeamId": "TR001",
      "status": "Backlog"
    },
    {
      "id": 8,
      "Tasks": "CA",
      "AssignedTo": "Ankit",
      "WorkRequestInfo": "chek",
      "TeamId": "TR002",
      "FeatureId": "FR008",
      "status": "Done"
    }
  ],
  "issues": [
    {
      "id": 1,
      "FeatureId": "FR001",
      "IssueId": "IR001",
      "Category": "Risks",
      "Description": "just an test",
      "AssignedTo": "Amit",
      "date": "Thu Jan 01 2019 05:30:00 GMT+0530 (India Standard Time)"
    },
    {
      "id": 2,
      "FeatureId": "FR001",
      "IssueId": "IR002",
      "Category": "Risks",
      "Description": "just an test",
      "AssignedTo": "Amit",
      "date": "Thu Jan 01 2019 05:30:00 GMT+0530 (India Standard Time)"
    },
    {
      "id": 3,
      "FeatureId": "FR002",
      "IssueId": "IR003",
      "Category": "Blockers",
      "Description": "just an test",
      "AssignedTo": "Amit",
      "date": "Thu Jan 01 2019 05:30:00 GMT+0530 (India Standard Time)"
    },
    {
      "id": 4,
      "FeatureId": "FR002",
      "IssueId": "IR004",
      "Category": "Blockers",
      "Description": "just an test",
      "AssignedTo": "Amit",
      "date": "Thu Jan 01 2019 05:30:00 GMT+0530 (India Standard Time)"
    },
    {
      "id": 5,
      "FeatureId": "FR001",
      "IssueId": "IR005",
      "Category": "Dependencies",
      "Description": "dependent on t01",
      "AssignedTo": "Ascensio",
      "date": "2018-11-30"
    }
  ],
  "tasks": [
    {
      "id": 1,
      "teamId": "TR001",
      "taskId": "SOS-20",
      "type": "Feature",
      "subType": "WorkRequest",
      "owner": "Alice",
      "summary": "main card implementation",
      "description": "main card implementation with all style and cs implementaion also aa demo",
      "sprint": "Sprint1",
      "release": "19E1",
      "status": "InProgress"
    },
    {
      "id": 5,
      "teamId": "TR001",
      "taskId": "SOS-21",
      "type": "Feature",
      "subType": "WorkRequest",
      "owner": "Amanda",
      "summary": "main card implementation 2",
      "description": "main card implementation with all style and cs implementaion also aa demo",
      "sprint": "Sprint2",
      "release": "19E1",
      "status": "Backlog"
    },
    {
      "id": 2,
      "teamId": "TR001",
      "taskId": "SOS-22",
      "type": "Feature",
      "subType": "WorkRequest",
      "owner": "Walis",
      "description": "main card implementation with all style and cs implementaion also aa demo",
      "sprint": "Sprint3",
      "release": "19E1",
      "status": "Done"
    },
    {
      "id": 3,
      "teamId": "TR001",
      "taskId": "SOS-23",
      "type": "Feature",
      "subType": "WorkRequest",
      "owner": "Tenny",
      "description": "main card implementation with all style and cs implementaion also aa demo",
      "sprint": "Sprint4",
      "release": "19E1",
      "status": "InProgress"
    },
    {
      "id": 4,
      "teamId": "TR001",
      "taskId": "SOS-24",
      "type": "Feature",
      "subType": "WorkRequest",
      "owner": "Alice",
      "summary": "main card implementation",
      "description": "main card implementation with all style and cs implementaion also aa demo",
      "sprint": "Sprint5",
      "release": "19E1",
      "status": "Backlog"
    },
    {
      "teamId": "TR002",
      "taskId": "SOS-5698",
      "type": "Issue",
      "subType": "Dependencies",
      "owner": "Amba",
      "summary": "summary demo",
      "description": "description demo",
      "sprint": "Sprint2",
      "release": "19E2",
      "status": "Backlog",
      "id": 6
    },
    {
      "teamId": "TR002",
      "taskId": "SOS-7584",
      "type": "Feature",
      "subType": "CI",
      "owner": "Amitq",
      "summary": "",
      "description": "octhohorpe",
      "sprint": "Sprint1",
      "release": "19E1",
      "status": "Backlog",
      "id": 7
    },
    {
      "teamId": "T869",
      "taskId": "SOS-5474",
      "type": "Feature",
      "subType": "WorkRequest",
      "owner": "chan",
      "summary": "",
      "description": "task checker",
      "sprint": "Sprint1",
      "release": "19E1",
      "status": "Backlog",
      "id": 8
    },
    {
      "teamId": "T41",
      "taskId": "SOS-2897",
      "type": "Issue",
      "subType": "Dependencies",
      "owner": "adf",
      "summary": "",
      "description": "checker",
      "sprint": "Sprint2",
      "release": "19E1",
      "status": "Backlog",
      "id": 9
    },
    {
      "teamId": "TR003",
      "taskId": "SOS-9486",
      "type": "Feature",
      "subType": "WorkRequest",
      "owner": "agghh",
      "summary": "",
      "description": "champ",
      "sprint": "Sprint1",
      "release": "19E1",
      "status": "Backlog",
      "id": 10
    }
  ]
}